[
    {
        "text": "KedaiUhat Dan Runcit CHONG HWA",
        "bbox": [
            [
                171.0,
                181.0
            ],
            [
                786.0,
                181.0
            ],
            [
                786.0,
                219.0
            ],
            [
                171.0,
                219.0
            ]
        ],
        "confidence": 0.9356905221939087
    },
    {
        "text": "3Jalan Perdana 5 Taman Indah Perdana",
        "bbox": [
            [
                76.0,
                234.0
            ],
            [
                860.0,
                234.0
            ],
            [
                860.0,
                272.0
            ],
            [
                76.0,
                272.0
            ]
        ],
        "confidence": 0.9199902415275574
    },
    {
        "text": "Kepong52100KL.",
        "bbox": [
            [
                305.0,
                283.0
            ],
            [
                646.0,
                281.0
            ],
            [
                647.0,
                321.0
            ],
            [
                305.0,
                323.0
            ]
        ],
        "confidence": 0.9424737095832825
    },
    {
        "text": "Telephone N0.03-62801198",
        "bbox": [
            [
                231.0,
                332.0
            ],
            [
                728.0,
                332.0
            ],
            [
                728.0,
                370.0
            ],
            [
                231.0,
                370.0
            ]
        ],
        "confidence": 0.9105713367462158
    },
    {
        "text": "GST No.001379917824",
        "bbox": [
            [
                268.0,
                383.0
            ],
            [
                670.0,
                383.0
            ],
            [
                670.0,
                423.0
            ],
            [
                268.0,
                423.0
            ]
        ],
        "confidence": 0.9424579739570618
    },
    {
        "text": "33037",
        "bbox": [
            [
                344.0,
                476.0
            ],
            [
                456.0,
                476.0
            ],
            [
                456.0,
                525.0
            ],
            [
                344.0,
                525.0
            ]
        ],
        "confidence": 0.998609185218811
    },
    {
        "text": "Receipt:",
        "bbox": [
            [
                45.0,
                479.0
            ],
            [
                212.0,
                479.0
            ],
            [
                212.0,
                525.0
            ],
            [
                45.0,
                525.0
            ]
        ],
        "confidence": 0.9743647575378418
    },
    {
        "text": "Date;",
        "bbox": [
            [
                43.0,
                528.0
            ],
            [
                151.0,
                528.0
            ],
            [
                151.0,
                576.0
            ],
            [
                43.0,
                576.0
            ]
        ],
        "confidence": 0.911321759223938
    },
    {
        "text": "0ct3.201612:16:25PM",
        "bbox": [
            [
                347.0,
                530.0
            ],
            [
                811.0,
                526.0
            ],
            [
                812.0,
                566.0
            ],
            [
                348.0,
                570.0
            ]
        ],
        "confidence": 0.9065887928009033
    },
    {
        "text": "CW01",
        "bbox": [
            [
                346.0,
                578.0
            ],
            [
                433.0,
                578.0
            ],
            [
                433.0,
                621.0
            ],
            [
                346.0,
                621.0
            ]
        ],
        "confidence": 0.9407312870025635
    },
    {
        "text": "Terminal:",
        "bbox": [
            [
                44.0,
                580.0
            ],
            [
                228.0,
                575.0
            ],
            [
                229.0,
                623.0
            ],
            [
                45.0,
                627.0
            ]
        ],
        "confidence": 0.9265316724777222
    },
    {
        "text": "Employee",
        "bbox": [
            [
                346.0,
                627.0
            ],
            [
                511.0,
                627.0
            ],
            [
                511.0,
                674.0
            ],
            [
                346.0,
                674.0
            ]
        ],
        "confidence": 0.9742400050163269
    },
    {
        "text": "Served by:",
        "bbox": [
            [
                45.0,
                629.0
            ],
            [
                249.0,
                629.0
            ],
            [
                249.0,
                674.0
            ],
            [
                45.0,
                674.0
            ]
        ],
        "confidence": 0.9122083783149719
    },
    {
        "text": "Price",
        "bbox": [
            [
                442.0,
                719.0
            ],
            [
                556.0,
                724.0
            ],
            [
                554.0,
                773.0
            ],
            [
                440.0,
                768.0
            ]
        ],
        "confidence": 0.9973899722099304
    },
    {
        "text": "Qty",
        "bbox": [
            [
                621.0,
                721.0
            ],
            [
                695.0,
                721.0
            ],
            [
                695.0,
                776.0
            ],
            [
                621.0,
                776.0
            ]
        ],
        "confidence": 0.9919312000274658
    },
    {
        "text": "Value",
        "bbox": [
            [
                784.0,
                721.0
            ],
            [
                893.0,
                721.0
            ],
            [
                893.0,
                772.0
            ],
            [
                784.0,
                772.0
            ]
        ],
        "confidence": 0.918327808380127
    },
    {
        "text": "Item",
        "bbox": [
            [
                43.0,
                723.0
            ],
            [
                134.0,
                723.0
            ],
            [
                134.0,
                774.0
            ],
            [
                43.0,
                774.0
            ]
        ],
        "confidence": 0.9833269119262695
    },
    {
        "text": "RM33.90",
        "bbox": [
            [
                742.0,
                821.0
            ],
            [
                891.0,
                821.0
            ],
            [
                891.0,
                868.0
            ],
            [
                742.0,
                868.0
            ]
        ],
        "confidence": 0.9793577790260315
    },
    {
        "text": "RM33.90",
        "bbox": [
            [
                401.0,
                823.0
            ],
            [
                554.0,
                819.0
            ],
            [
                556.0,
                868.0
            ],
            [
                403.0,
                872.0
            ]
        ],
        "confidence": 0.9922584891319275
    },
    {
        "text": "x1",
        "bbox": [
            [
                639.0,
                823.0
            ],
            [
                695.0,
                823.0
            ],
            [
                695.0,
                872.0
            ],
            [
                639.0,
                872.0
            ]
        ],
        "confidence": 0.7073888778686523
    },
    {
        "text": "Liguid Medicine",
        "bbox": [
            [
                49.0,
                829.0
            ],
            [
                348.0,
                829.0
            ],
            [
                348.0,
                868.0
            ],
            [
                49.0,
                868.0
            ]
        ],
        "confidence": 0.9240959882736206
    },
    {
        "text": "Items count:1",
        "bbox": [
            [
                46.0,
                927.0
            ],
            [
                330.0,
                923.0
            ],
            [
                330.0,
                968.0
            ],
            [
                47.0,
                972.0
            ]
        ],
        "confidence": 0.9462125301361084
    },
    {
        "text": "RM33.90",
        "bbox": [
            [
                740.0,
                1017.0
            ],
            [
                899.0,
                1017.0
            ],
            [
                899.0,
                1104.0
            ],
            [
                740.0,
                1104.0
            ]
        ],
        "confidence": 0.9228886961936951
    },
    {
        "text": "Total Sales Incl.GST e 6%",
        "bbox": [
            [
                54.0,
                1029.0
            ],
            [
                567.0,
                1029.0
            ],
            [
                567.0,
                1093.0
            ],
            [
                54.0,
                1093.0
            ]
        ],
        "confidence": 0.8411080837249756
    },
    {
        "text": "Cash",
        "bbox": [
            [
                45.0,
                1099.0
            ],
            [
                138.0,
                1099.0
            ],
            [
                138.0,
                1148.0
            ],
            [
                45.0,
                1148.0
            ]
        ],
        "confidence": 0.9959210157394409
    },
    {
        "text": "RM100.00",
        "bbox": [
            [
                722.0,
                1148.0
            ],
            [
                891.0,
                1148.0
            ],
            [
                891.0,
                1193.0
            ],
            [
                722.0,
                1193.0
            ]
        ],
        "confidence": 0.979231059551239
    },
    {
        "text": "Tendered:",
        "bbox": [
            [
                45.0,
                1149.0
            ],
            [
                229.0,
                1149.0
            ],
            [
                229.0,
                1195.0
            ],
            [
                45.0,
                1195.0
            ]
        ],
        "confidence": 0.9890428185462952
    },
    {
        "text": "Change:",
        "bbox": [
            [
                44.0,
                1196.0
            ],
            [
                193.0,
                1201.0
            ],
            [
                191.0,
                1248.0
            ],
            [
                42.0,
                1243.0
            ]
        ],
        "confidence": 0.9917605519294739
    },
    {
        "text": "RM66.10",
        "bbox": [
            [
                739.0,
                1199.0
            ],
            [
                892.0,
                1194.0
            ],
            [
                894.0,
                1242.0
            ],
            [
                741.0,
                1246.0
            ]
        ],
        "confidence": 0.9877384305000305
    },
    {
        "text": "RM31.98",
        "bbox": [
            [
                746.0,
                1297.0
            ],
            [
                889.0,
                1297.0
            ],
            [
                889.0,
                1338.0
            ],
            [
                746.0,
                1338.0
            ]
        ],
        "confidence": 0.9903744459152222
    },
    {
        "text": "Nett of Tax",
        "bbox": [
            [
                49.0,
                1299.0
            ],
            [
                285.0,
                1299.0
            ],
            [
                285.0,
                1338.0
            ],
            [
                49.0,
                1338.0
            ]
        ],
        "confidence": 0.9401308298110962
    },
    {
        "text": "RM1.92",
        "bbox": [
            [
                763.0,
                1344.0
            ],
            [
                893.0,
                1344.0
            ],
            [
                893.0,
                1391.0
            ],
            [
                763.0,
                1391.0
            ]
        ],
        "confidence": 0.9942245483398438
    },
    {
        "text": "%9GST",
        "bbox": [
            [
                49.0,
                1350.0
            ],
            [
                227.0,
                1350.0
            ],
            [
                227.0,
                1389.0
            ],
            [
                49.0,
                1389.0
            ]
        ],
        "confidence": 0.6236192584037781
    },
    {
        "text": "SR",
        "bbox": [
            [
                43.0,
                1440.0
            ],
            [
                95.0,
                1440.0
            ],
            [
                95.0,
                1491.0
            ],
            [
                43.0,
                1491.0
            ]
        ],
        "confidence": 0.9935123920440674
    },
    {
        "text": "RM31.98",
        "bbox": [
            [
                507.0,
                1444.0
            ],
            [
                649.0,
                1444.0
            ],
            [
                649.0,
                1485.0
            ],
            [
                507.0,
                1485.0
            ]
        ],
        "confidence": 0.9853166341781616
    },
    {
        "text": "RM1.92",
        "bbox": [
            [
                765.0,
                1444.0
            ],
            [
                891.0,
                1444.0
            ],
            [
                891.0,
                1485.0
            ],
            [
                765.0,
                1485.0
            ]
        ],
        "confidence": 0.9953029751777649
    },
    {
        "text": "RMO.00",
        "bbox": [
            [
                524.0,
                1493.0
            ],
            [
                650.0,
                1493.0
            ],
            [
                650.0,
                1535.0
            ],
            [
                524.0,
                1535.0
            ]
        ],
        "confidence": 0.9740390181541443
    },
    {
        "text": "RMO.00",
        "bbox": [
            [
                763.0,
                1493.0
            ],
            [
                889.0,
                1493.0
            ],
            [
                889.0,
                1535.0
            ],
            [
                763.0,
                1535.0
            ]
        ],
        "confidence": 0.9921104311943054
    },
    {
        "text": "Standard Rated Tax",
        "bbox": [
            [
                47.0,
                1497.0
            ],
            [
                408.0,
                1497.0
            ],
            [
                408.0,
                1535.0
            ],
            [
                47.0,
                1535.0
            ]
        ],
        "confidence": 0.9440134763717651
    },
    {
        "text": "ZR",
        "bbox": [
            [
                45.0,
                1542.0
            ],
            [
                91.0,
                1542.0
            ],
            [
                91.0,
                1584.0
            ],
            [
                45.0,
                1584.0
            ]
        ],
        "confidence": 0.9922248721122742
    },
    {
        "text": "RMO.00",
        "bbox": [
            [
                524.0,
                1542.0
            ],
            [
                650.0,
                1542.0
            ],
            [
                650.0,
                1584.0
            ],
            [
                524.0,
                1584.0
            ]
        ],
        "confidence": 0.9789295792579651
    },
    {
        "text": "RMO.00",
        "bbox": [
            [
                763.0,
                1542.0
            ],
            [
                891.0,
                1542.0
            ],
            [
                891.0,
                1584.0
            ],
            [
                763.0,
                1584.0
            ]
        ],
        "confidence": 0.9888032078742981
    },
    {
        "text": "RMO.00",
        "bbox": [
            [
                522.0,
                1589.0
            ],
            [
                652.0,
                1589.0
            ],
            [
                652.0,
                1636.0
            ],
            [
                522.0,
                1636.0
            ]
        ],
        "confidence": 0.9696323871612549
    },
    {
        "text": "RMO.00",
        "bbox": [
            [
                763.0,
                1591.0
            ],
            [
                891.0,
                1591.0
            ],
            [
                891.0,
                1633.0
            ],
            [
                763.0,
                1633.0
            ]
        ],
        "confidence": 0.9880314469337463
    },
    {
        "text": "Zero Rated Tax (ZR",
        "bbox": [
            [
                47.0,
                1593.0
            ],
            [
                408.0,
                1591.0
            ],
            [
                408.0,
                1631.0
            ],
            [
                47.0,
                1633.0
            ]
        ],
        "confidence": 0.9073331356048584
    },
    {
        "text": "Thank You",
        "bbox": [
            [
                371.0,
                1682.0
            ],
            [
                573.0,
                1682.0
            ],
            [
                573.0,
                1735.0
            ],
            [
                371.0,
                1735.0
            ]
        ],
        "confidence": 0.9468285441398621
    }
]