[
    {
        "text": "POPULAR BOOK",
        "bbox": [
            [
                143.0,
                121.0
            ],
            [
                557.0,
                131.0
            ],
            [
                556.0,
                179.0
            ],
            [
                142.0,
                169.0
            ]
        ],
        "confidence": 0.9601671695709229
    },
    {
        "text": "CO.MSDNBHD",
        "bbox": [
            [
                105.0,
                184.0
            ],
            [
                632.0,
                196.0
            ],
            [
                631.0,
                248.0
            ],
            [
                104.0,
                237.0
            ]
        ],
        "confidence": 0.9796269536018372
    },
    {
        "text": "Co.No.113825-W",
        "bbox": [
            [
                190.0,
                248.0
            ],
            [
                508.0,
                252.0
            ],
            [
                508.0,
                285.0
            ],
            [
                190.0,
                280.0
            ]
        ],
        "confidence": 0.9636354446411133
    },
    {
        "text": "GST Reg No. 001492992000)",
        "bbox": [
            [
                122.0,
                284.0
            ],
            [
                578.0,
                292.0
            ],
            [
                577.0,
                323.0
            ],
            [
                122.0,
                315.0
            ]
        ],
        "confidence": 0.9285431504249573
    },
    {
        "text": "No 8Jalan 7/l18BDesa Tun Razak",
        "bbox": [
            [
                46.0,
                321.0
            ],
            [
                649.0,
                333.0
            ],
            [
                648.0,
                363.0
            ],
            [
                46.0,
                352.0
            ]
        ],
        "confidence": 0.9321308732032776
    },
    {
        "text": "56000 Kuala Lumpur Malaysia",
        "bbox": [
            [
                99.0,
                360.0
            ],
            [
                597.0,
                371.0
            ],
            [
                596.0,
                402.0
            ],
            [
                98.0,
                391.0
            ]
        ],
        "confidence": 0.9435845613479614
    },
    {
        "text": "SUNWAY VELOCITY",
        "bbox": [
            [
                205.0,
                401.0
            ],
            [
                473.0,
                406.0
            ],
            [
                473.0,
                439.0
            ],
            [
                204.0,
                434.0
            ]
        ],
        "confidence": 0.9696254730224609
    },
    {
        "text": "Tel :03-9201 6281/6920",
        "bbox": [
            [
                151.0,
                478.0
            ],
            [
                559.0,
                488.0
            ],
            [
                558.0,
                520.0
            ],
            [
                150.0,
                511.0
            ]
        ],
        "confidence": 0.9254430532455444
    },
    {
        "text": "14/03/1812:52",
        "bbox": [
            [
                27.0,
                555.0
            ],
            [
                277.0,
                560.0
            ],
            [
                276.0,
                593.0
            ],
            [
                27.0,
                588.0
            ]
        ],
        "confidence": 0.9791842699050903
    },
    {
        "text": "SlipNo.0040081037",
        "bbox": [
            [
                325.0,
                561.0
            ],
            [
                681.0,
                568.0
            ],
            [
                680.0,
                599.0
            ],
            [
                324.0,
                592.0
            ]
        ],
        "confidence": 0.9786862730979919
    },
    {
        "text": "LEE WIN LEE",
        "bbox": [
            [
                24.0,
                594.0
            ],
            [
                223.0,
                599.0
            ],
            [
                223.0,
                631.0
            ],
            [
                23.0,
                626.0
            ]
        ],
        "confidence": 0.9234610199928284
    },
    {
        "text": "Trans:90243",
        "bbox": [
            [
                379.0,
                601.0
            ],
            [
                594.0,
                605.0
            ],
            [
                593.0,
                637.0
            ],
            [
                378.0,
                634.0
            ]
        ],
        "confidence": 0.9575555920600891
    },
    {
        "text": "Description",
        "bbox": [
            [
                23.0,
                669.0
            ],
            [
                220.0,
                674.0
            ],
            [
                219.0,
                706.0
            ],
            [
                22.0,
                701.0
            ]
        ],
        "confidence": 0.992191731929779
    },
    {
        "text": "Amount",
        "bbox": [
            [
                517.0,
                678.0
            ],
            [
                629.0,
                684.0
            ],
            [
                627.0,
                717.0
            ],
            [
                515.0,
                712.0
            ]
        ],
        "confidence": 0.9969573616981506
    },
    {
        "text": "CBE Rubber Band200gm",
        "bbox": [
            [
                22.0,
                749.0
            ],
            [
                375.0,
                754.0
            ],
            [
                375.0,
                785.0
            ],
            [
                22.0,
                780.0
            ]
        ],
        "confidence": 0.9463521838188171
    },
    {
        "text": "7.95T",
        "bbox": [
            [
                568.0,
                757.0
            ],
            [
                681.0,
                757.0
            ],
            [
                681.0,
                791.0
            ],
            [
                568.0,
                791.0
            ]
        ],
        "confidence": 0.9925354719161987
    },
    {
        "text": "Total RM Incl.of GST",
        "bbox": [
            [
                21.0,
                826.0
            ],
            [
                396.0,
                831.0
            ],
            [
                395.0,
                863.0
            ],
            [
                20.0,
                858.0
            ]
        ],
        "confidence": 0.8963252902030945
    },
    {
        "text": "7.95",
        "bbox": [
            [
                568.0,
                832.0
            ],
            [
                646.0,
                836.0
            ],
            [
                644.0,
                873.0
            ],
            [
                566.0,
                869.0
            ]
        ],
        "confidence": 0.9909967184066772
    },
    {
        "text": "Cash",
        "bbox": [
            [
                21.0,
                866.0
            ],
            [
                95.0,
                866.0
            ],
            [
                95.0,
                900.0
            ],
            [
                21.0,
                900.0
            ]
        ],
        "confidence": 0.9975261688232422
    },
    {
        "text": "-10.00",
        "bbox": [
            [
                534.0,
                872.0
            ],
            [
                644.0,
                876.0
            ],
            [
                643.0,
                910.0
            ],
            [
                533.0,
                906.0
            ]
        ],
        "confidence": 0.9895965456962585
    },
    {
        "text": "CHANGE",
        "bbox": [
            [
                21.0,
                905.0
            ],
            [
                131.0,
                905.0
            ],
            [
                131.0,
                939.0
            ],
            [
                21.0,
                939.0
            ]
        ],
        "confidence": 0.9978418350219727
    },
    {
        "text": "2.05",
        "bbox": [
            [
                565.0,
                912.0
            ],
            [
                644.0,
                912.0
            ],
            [
                644.0,
                948.0
            ],
            [
                565.0,
                948.0
            ]
        ],
        "confidence": 0.9979321956634521
    },
    {
        "text": "Item Count",
        "bbox": [
            [
                19.0,
                978.0
            ],
            [
                196.0,
                982.0
            ],
            [
                196.0,
                1016.0
            ],
            [
                19.0,
                1012.0
            ]
        ],
        "confidence": 0.9765222668647766
    },
    {
        "text": "1",
        "bbox": [
            [
                616.0,
                989.0
            ],
            [
                643.0,
                989.0
            ],
            [
                643.0,
                1022.0
            ],
            [
                616.0,
                1022.0
            ]
        ],
        "confidence": 0.9910470843315125
    },
    {
        "text": "GST Summary",
        "bbox": [
            [
                17.0,
                1015.0
            ],
            [
                219.0,
                1022.0
            ],
            [
                218.0,
                1054.0
            ],
            [
                15.0,
                1047.0
            ]
        ],
        "confidence": 0.9492035508155823
    },
    {
        "text": "Amount RM",
        "bbox": [
            [
                247.0,
                1020.0
            ],
            [
                442.0,
                1023.0
            ],
            [
                441.0,
                1057.0
            ],
            [
                247.0,
                1054.0
            ]
        ],
        "confidence": 0.9632115960121155
    },
    {
        "text": "TaxRM",
        "bbox": [
            [
                494.0,
                1023.0
            ],
            [
                640.0,
                1026.0
            ],
            [
                639.0,
                1059.0
            ],
            [
                493.0,
                1055.0
            ]
        ],
        "confidence": 0.9933291673660278
    },
    {
        "text": "T@6%",
        "bbox": [
            [
                15.0,
                1052.0
            ],
            [
                129.0,
                1056.0
            ],
            [
                127.0,
                1094.0
            ],
            [
                14.0,
                1090.0
            ]
        ],
        "confidence": 0.9942024946212769
    },
    {
        "text": "7.50",
        "bbox": [
            [
                370.0,
                1060.0
            ],
            [
                446.0,
                1060.0
            ],
            [
                446.0,
                1095.0
            ],
            [
                370.0,
                1095.0
            ]
        ],
        "confidence": 0.9950717687606812
    },
    {
        "text": "0.45",
        "bbox": [
            [
                565.0,
                1065.0
            ],
            [
                641.0,
                1065.0
            ],
            [
                641.0,
                1100.0
            ],
            [
                565.0,
                1100.0
            ]
        ],
        "confidence": 0.996265172958374
    },
    {
        "text": "Total Savings",
        "bbox": [
            [
                17.0,
                1131.0
            ],
            [
                247.0,
                1137.0
            ],
            [
                246.0,
                1173.0
            ],
            [
                15.0,
                1166.0
            ]
        ],
        "confidence": 0.9601736068725586
    },
    {
        "text": "0.00",
        "bbox": [
            [
                563.0,
                1140.0
            ],
            [
                642.0,
                1144.0
            ],
            [
                640.0,
                1179.0
            ],
            [
                561.0,
                1175.0
            ]
        ],
        "confidence": 0.9919837117195129
    },
    {
        "text": "BE A POPULAR CARD MEMBER",
        "bbox": [
            [
                121.0,
                1214.0
            ],
            [
                548.0,
                1223.0
            ],
            [
                547.0,
                1254.0
            ],
            [
                120.0,
                1244.0
            ]
        ],
        "confidence": 0.9344689846038818
    },
    {
        "text": "AND ENJOY SPECIAL DISCOUNTS",
        "bbox": [
            [
                106.0,
                1254.0
            ],
            [
                579.0,
                1262.0
            ],
            [
                579.0,
                1293.0
            ],
            [
                106.0,
                1285.0
            ]
        ],
        "confidence": 0.9590865969657898
    },
    {
        "text": "THANK YOU. PLEASE COME AGAIN.",
        "bbox": [
            [
                86.0,
                1291.0
            ],
            [
                589.0,
                1299.0
            ],
            [
                588.0,
                1329.0
            ],
            [
                85.0,
                1321.0
            ]
        ],
        "confidence": 0.9383753538131714
    },
    {
        "text": "www.popular.com.my",
        "bbox": [
            [
                173.0,
                1332.0
            ],
            [
                494.0,
                1339.0
            ],
            [
                493.0,
                1370.0
            ],
            [
                172.0,
                1363.0
            ]
        ],
        "confidence": 0.9851288199424744
    },
    {
        "text": "Buy Chinese books online",
        "bbox": [
            [
                121.0,
                1369.0
            ],
            [
                545.0,
                1377.0
            ],
            [
                544.0,
                1408.0
            ],
            [
                120.0,
                1400.0
            ]
        ],
        "confidence": 0.9616156220436096
    },
    {
        "text": "www.popularonline.com.my",
        "bbox": [
            [
                119.0,
                1409.0
            ],
            [
                545.0,
                1417.0
            ],
            [
                544.0,
                1448.0
            ],
            [
                118.0,
                1440.0
            ]
        ],
        "confidence": 0.9704416394233704
    }
]